kfp_doctor/__init__.py
kfp_doctor/analyzer.py
kfp_doctor/autofix.py
kfp_doctor/cli.py
kfp_doctor/config.py
kfp_doctor/config_generator.py
kfp_doctor/parser.py
kfp_doctor-1.0.0.dist-info/METADATA
kfp_doctor-1.0.0.dist-info/WHEEL
kfp_doctor-1.0.0.dist-info/entry_points.txt
kfp_doctor-1.0.0.dist-info/licenses/LICENSE
kfp_doctor-1.0.0.dist-info/RECORD
