Metadata-Version: 2.4
Name: kfp-doctor
Version: 1.0.0
Summary: A comprehensive linter for healthy Kubeflow Pipelines with advanced analysis and auto-fix capabilities
Project-URL: Homepage, https://github.com/eswarchandravidyasagar/kfp-doctor
Project-URL: Repository, https://github.com/eswarchandravidyasagar/kfp-doctor
Project-URL: Issues, https://github.com/eswarchandravidyasagar/kfp-doctor/issues
Project-URL: Documentation, https://github.com/eswarchandravidyasagar/kfp-doctor#readme
Project-URL: Changelog, https://github.com/eswarchandravidyasagar/kfp-doctor/blob/main/CHANGELOG.md
Author-email: Eswar Attuluri <eswarattuluri@gmail.com>
License: MIT
License-File: LICENSE
Keywords: kubeflow,kubernetes,linter,mlops,pipelines
Classifier: Development Status :: 4 - Beta
Classifier: Intended Audience :: Developers
Classifier: License :: OSI Approved :: MIT License
Classifier: Operating System :: OS Independent
Classifier: Programming Language :: Python :: 3
Classifier: Programming Language :: Python :: 3.8
Classifier: Programming Language :: Python :: 3.9
Classifier: Programming Language :: Python :: 3.10
Classifier: Programming Language :: Python :: 3.11
Classifier: Programming Language :: Python :: 3.12
Classifier: Topic :: Scientific/Engineering :: Artificial Intelligence
Classifier: Topic :: Software Development :: Quality Assurance
Requires-Python: >=3.8.1
Requires-Dist: build>=1.2.2.post1
Requires-Dist: click>=8.0.0
Requires-Dist: pyyaml>=6.0
Requires-Dist: rich>=13.0.0
Provides-Extra: dev
Requires-Dist: black>=23.0.0; extra == 'dev'
Requires-Dist: flake8>=6.0.0; extra == 'dev'
Requires-Dist: isort>=5.12.0; extra == 'dev'
Requires-Dist: mypy>=1.0.0; extra == 'dev'
Requires-Dist: pre-commit>=3.0.0; extra == 'dev'
Requires-Dist: pytest-cov>=4.0.0; extra == 'dev'
Requires-Dist: pytest>=7.0.0; extra == 'dev'
Provides-Extra: test
Requires-Dist: pytest-cov>=4.0.0; extra == 'test'
Requires-Dist: pytest>=7.0.0; extra == 'test'
